MANIFEST.in
README.md
setup.py
django_sendsmsru.egg-info/PKG-INFO
django_sendsmsru.egg-info/SOURCES.txt
django_sendsmsru.egg-info/dependency_links.txt
django_sendsmsru.egg-info/not-zip-safe
django_sendsmsru.egg-info/requires.txt
django_sendsmsru.egg-info/top_level.txt
sendsmsru/__init__.py
sendsmsru/backends/__init__.py
sendsmsru/backends/infosmskaru.py
sendsmsru/backends/websmsru.py