Metadata-Version: 1.0
Name: django-sendsmsru
Version: 0.1.9
Summary: Russian backends for django-sendsms
Home-page: http://github.com/suvit/django-sendsmsru
Author: Victor Safronovich
Author-email: vsafronovich@gmail.com
License: MIT
Platform: UNKNOWN
